__init__.py
github.py
tiktoken.py
alita_tools/__init__.py
alita_tools/elitea_base.py
alita_tools/ado/__init__.py
alita_tools/ado/utils.py
alita_tools/ado/repos/__init__.py
alita_tools/ado/repos/repos_wrapper.py
alita_tools/ado/test_plan/__init__.py
alita_tools/ado/test_plan/test_plan_wrapper.py
alita_tools/ado/wiki/__init__.py
alita_tools/ado/wiki/ado_wrapper.py
alita_tools/ado/work_item/__init__.py
alita_tools/ado/work_item/ado_wrapper.py
alita_tools/advanced_jira_mining/__init__.py
alita_tools/advanced_jira_mining/data_mining_wrapper.py
alita_tools/atlassian/__init__.py
alita_tools/atlassian/api_wrapper.py
alita_tools/atlassian/executor/code_environment.py
alita_tools/atlassian/executor/code_executor.py
alita_tools/atlassian/generator/base.py
alita_tools/atlassian/generator/code_validator.py
alita_tools/azure_ai/__init__.py
alita_tools/azure_ai/search/__init__.py
alita_tools/azure_ai/search/api_wrapper.py
alita_tools/base/__init__.py
alita_tools/base/tool.py
alita_tools/bitbucket/__init__.py
alita_tools/bitbucket/api_wrapper.py
alita_tools/bitbucket/bitbucket_constants.py
alita_tools/bitbucket/cloud_api_wrapper.py
alita_tools/bitbucket/tools.py
alita_tools/browser/__init__.py
alita_tools/browser/crawler.py
alita_tools/browser/duck_duck_go_search.py
alita_tools/browser/google_search_rag.py
alita_tools/browser/utils.py
alita_tools/browser/wiki.py
alita_tools/carrier/__init__.py
alita_tools/carrier/api_wrapper.py
alita_tools/carrier/backend_reports_tool.py
alita_tools/carrier/backend_tests_tool.py
alita_tools/carrier/carrier_sdk.py
alita_tools/carrier/excel_reporter.py
alita_tools/carrier/tickets_tool.py
alita_tools/carrier/tools.py
alita_tools/carrier/utils.py
alita_tools/chunkers/__init__.py
alita_tools/chunkers/models.py
alita_tools/chunkers/utils.py
alita_tools/chunkers/code/__init__.py
alita_tools/chunkers/code/codeparser.py
alita_tools/chunkers/code/constants.py
alita_tools/chunkers/code/treesitter/__init__.py
alita_tools/chunkers/code/treesitter/treesitter.py
alita_tools-0.3.224.dist-info/licenses/LICENSE
alita_tools-0.3.224.dist-info/METADATA
alita_tools-0.3.224.dist-info/WHEEL
alita_tools-0.3.224.dist-info/top_level.txt
alita_tools-0.3.224.dist-info/RECORD
